README.md
setup.cfg
setup.py
test_pypi/Test.py
test_pypi/__init__.py
test_pypi_dsoon.egg-info/PKG-INFO
test_pypi_dsoon.egg-info/SOURCES.txt
test_pypi_dsoon.egg-info/dependency_links.txt
test_pypi_dsoon.egg-info/top_level.txt