Metadata-Version: 2.1
Name: test-pypi-dsoon
Version: 0.3
Summary: A Hello World package
Home-page: https://github.com/dsoon/Pypi
Author: David Soon
Author-email: david.soon@outlook.com
License: UNKNOWN
Platform: UNKNOWN
Classifier: Programming Language :: Python :: 3.8
Classifier: License :: OSI Approved :: MIT License
Classifier: Operating System :: OS Independent
Requires-Python: >=3.6
